conector_mysql_sgd/__init__.py
conector_mysql_sgd/conector.py
conector_mysql_sgd-0.0.4.dist-info/METADATA
conector_mysql_sgd-0.0.4.dist-info/WHEEL
conector_mysql_sgd-0.0.4.dist-info/top_level.txt
conector_mysql_sgd-0.0.4.dist-info/RECORD
