Metadata-Version: 2.1
Name: conector-mysql-sgd
Version: 0.0.4
Requires-Dist: sqlalchemy
Requires-Dist: mysql-connector-python
Requires-Dist: pandas
